dblp_spider/__init__.py
dblp_spider/core/__init__.py
dblp_spider/core/article.py
dblp_spider/core/conference.py
DBLP_Spider-0.0.5.dist-info/LICENSE
DBLP_Spider-0.0.5.dist-info/METADATA
DBLP_Spider-0.0.5.dist-info/WHEEL
DBLP_Spider-0.0.5.dist-info/entry_points.txt
DBLP_Spider-0.0.5.dist-info/top_level.txt
DBLP_Spider-0.0.5.dist-info/RECORD
