Metadata-Version: 2.1
Name: DBLP-Spider
Version: 0.0.5
Summary: A spider tool for downloading the DBLP search results into local BibTeX files
Home-page: https://github.com/WangYihang/Platypus-Python
Author: Wang Yihang
Author-email: wangyihanger@gmail.com
License: UNKNOWN
Keywords: academic,research,spider,dblp,ccf
Platform: UNKNOWN
Classifier: Programming Language :: Python :: 3
Classifier: Development Status :: 5 - Production/Stable
Classifier: License :: OSI Approved :: MIT License
Requires-Python: >=3.6
Requires-Dist: bs4
Requires-Dist: requests
Requires-Dist: termcolor
